classic/aspects/__init__.py
classic/aspects/points.py
classic_aspects-0.0.1.dist-info/LICENSE
classic_aspects-0.0.1.dist-info/METADATA
classic_aspects-0.0.1.dist-info/WHEEL
classic_aspects-0.0.1.dist-info/top_level.txt
classic_aspects-0.0.1.dist-info/RECORD
