Metadata-Version: 2.1
Name: classic-aspects
Version: 0.0.1
Summary: Provides convenient utils for late decorating, based on idea of aspects-oriented programming
Home-page: https://github.com/variasov/classic_aspects
Author: Sergei Variasov
Author-email: variasov@gmail.com
License: UNKNOWN
Project-URL: Bug Tracker, https://github.com/variasov/classic_aspects/issues
Platform: UNKNOWN
Classifier: Programming Language :: Python :: 3.7
Classifier: License :: OSI Approved :: MIT License
Classifier: Operating System :: OS Independent
Classifier: Development Status :: 4 - Beta
Requires-Python: >=3.7
License-File: LICENSE
Provides-Extra: dev
Requires-Dist: pytest (~=6.2.5) ; extra == 'dev'
Requires-Dist: pytest-cov (~=2.12.1) ; extra == 'dev'
Requires-Dist: twine (~=3.4.2) ; extra == 'dev'
Requires-Dist: build (~=0.7.0) ; extra == 'dev'
